pombseen/__init__.py
pombseen/_version.py
pombseen/main.py
pombseen-0.2.0b0.dist-info/LICENSE
pombseen-0.2.0b0.dist-info/METADATA
pombseen-0.2.0b0.dist-info/WHEEL
pombseen-0.2.0b0.dist-info/top_level.txt
pombseen-0.2.0b0.dist-info/RECORD
