Metadata-Version: 2.1
Name: pombseen
Version: 0.2.0b0
Summary: Python implementation of pomBseen
Author-email: Timon Stegmaier <timonst2000@gmail.com>
License: BSD-3-Clause
Requires-Python: >=3.9
License-File: LICENSE
Requires-Dist: numpy
Requires-Dist: scikit-image
